{
    "meters": [
        {
            "authorization_uid": "794", 
            "base": {
                "billing_account": "2000000942", 
                "billing_address": "942 Main St, Anytown, CA 12345", 
                "billing_contact": "Anonymous User", 
                "meter_numbers": [
                    "3000000942"
                ], 
                "service_address": "942 #100 Main St, Anytown, CA 12345", 
                "service_class": "electric", 
                "service_identifier": "1000000942", 
                "service_tariff": "E1 X Residential Service"
            }, 
            "bill_count": 12, 
            "bill_coverage": [
                [
                    "2018-09-15T07:00:00.000000+00:00", 
                    "2018-09-20T07:00:00.000000+00:00"
                ], 
                [
                    "2018-09-21T07:00:00.000000+00:00", 
                    "2018-10-22T07:00:00.000000+00:00"
                ], 
                [
                    "2018-10-23T07:00:00.000000+00:00", 
                    "2018-11-20T08:00:00.000000+00:00"
                ], 
                [
                    "2018-11-21T08:00:00.000000+00:00", 
                    "2018-12-20T08:00:00.000000+00:00"
                ], 
                [
                    "2019-01-23T08:00:00.000000+00:00", 
                    "2019-02-21T08:00:00.000000+00:00"
                ], 
                [
                    "2019-02-22T08:00:00.000000+00:00", 
                    "2019-03-22T07:00:00.000000+00:00"
                ], 
                [
                    "2019-03-23T07:00:00.000000+00:00", 
                    "2019-04-23T07:00:00.000000+00:00"
                ], 
                [
                    "2019-04-24T07:00:00.000000+00:00", 
                    "2019-05-22T07:00:00.000000+00:00"
                ], 
                [
                    "2019-05-23T07:00:00.000000+00:00", 
                    "2019-06-21T07:00:00.000000+00:00"
                ], 
                [
                    "2019-06-22T07:00:00.000000+00:00", 
                    "2019-07-23T07:00:00.000000+00:00"
                ], 
                [
                    "2019-08-23T07:00:00.000000+00:00", 
                    "2019-09-23T07:00:00.000000+00:00"
                ], 
                [
                    "2019-11-21T08:00:00.000000+00:00", 
                    "2019-12-20T08:00:00.000000+00:00"
                ]
            ], 
            "bill_sources": [
                "pdf"
            ], 
            "blocks": [
                "base"
            ], 
            "created": "2020-01-29T00:00:00.000000+00:00", 
            "exports": {}, 
            "exports_list": [], 
            "interval_count": 14688, 
            "interval_coverage": [
                [
                    "2018-04-20T14:00:00.000000+00:00", 
                    "2018-04-26T14:00:00.000000+00:00"
                ], 
                [
                    "2018-05-08T14:00:00.000000+00:00", 
                    "2018-08-30T14:00:00.000000+00:00"
                ], 
                [
                    "2018-09-14T14:00:00.000000+00:00", 
                    "2018-11-04T08:00:00.000000+00:00"
                ], 
                [
                    "2018-11-04T09:00:00.000000+00:00", 
                    "2019-11-03T08:00:00.000000+00:00"
                ]
            ], 
            "interval_sources": [
                "greenbutton_cmd"
            ], 
            "is_activated": true, 
            "is_archived": false, 
            "notes": [], 
            "ongoing_monitoring": {
                "frequency": "off", 
                "next_prepay": null, 
                "next_refresh": null, 
                "prepay": null
            }, 
            "status": "updated", 
            "status_message": "Anonymous service generated", 
            "status_ts": "2020-01-29T00:00:00.000000+00:00", 
            "uid": "942", 
            "user_email": "anonymous@customer.com", 
            "user_uid": 1, 
            "utility": "SVCE"
        }
    ], 
    "next": null
}